[
    {
      "id": 1,
      "icon": "/icons/0001.png",
      "name": "蘋果",
      "weight": 100,
      "effect": {    
        "勇敢": 3,
        "堅毅": 0,
        "冷靜": 0,
        "靈巧": 0,
        "奉獻": 0
      }
    },
    {
      "id": 2,
      "icon": "/icons/0002.png",
      "name": "橘子",
      "weight": 100,
      "effect": {    
        "勇敢": 0,
        "堅毅": 0,
        "冷靜": 0,
        "靈巧": 3,
        "奉獻": 0
      }
    },
    {
      "id": 3,
      "icon": "/icons/0003.png",
      "name": "醃漬橘子",
      "weight": 30,
      "effect": {    
        "勇敢": 0,
        "堅毅": 0,
        "冷靜": 0,
        "靈巧": 10,
        "奉獻": 0
      }
    }
  ]